smolorm/__init__.py
smolorm/connection.py
smolorm/expressions.py
smolorm/orm.py
smolorm/sqlmodel.py
smolorm-0.0.2.dist-info/licenses/LICENSE
smolorm-0.0.2.dist-info/METADATA
smolorm-0.0.2.dist-info/WHEEL
smolorm-0.0.2.dist-info/top_level.txt
smolorm-0.0.2.dist-info/RECORD
