Metadata-Version: 2.4
Name: smolorm
Version: 0.0.2
Summary: SmolORM is a small ORM for Python
Author-email: BADINI Rachid Rodrigue <bsrodrigue@gmail.com>
License: MIT
Project-URL: Repository, https://github.com/bsrodrigue/smolorm
Classifier: Programming Language :: Python :: 3
Classifier: License :: OSI Approved :: MIT License
Classifier: Operating System :: OS Independent
Requires-Python: >=3.8
License-File: LICENSE
Requires-Dist: SQLAlchemy==2.0.42
Dynamic: license-file
